README.md
gif_frames.py
setup.py
gif_frames.egg-info/PKG-INFO
gif_frames.egg-info/SOURCES.txt
gif_frames.egg-info/dependency_links.txt
gif_frames.egg-info/entry_points.txt
gif_frames.egg-info/requires.txt
gif_frames.egg-info/top_level.txt