Metadata-Version: 2.1
Name: gif-frames
Version: 0.1.0
Summary: Extract frames from gif image.
Home-page: UNKNOWN
Author: zencore
Author-email: dobetter@zencore.cn
License: MIT
Keywords: gif-frames,gif
Platform: UNKNOWN
Classifier: Development Status :: 5 - Production/Stable
Classifier: Intended Audience :: Developers
Classifier: Topic :: Software Development :: Libraries :: Python Modules
Classifier: License :: OSI Approved :: MIT License
Classifier: Programming Language :: Python :: 3
Classifier: Programming Language :: Python :: 3 :: Only
Requires: click
Requires: pillow
